loki_api_client/__init__.py
loki_api_client/loki_connect.py
loki_api_client-0.1.0.dist-info/AUTHORS.rst
loki_api_client-0.1.0.dist-info/LICENSE.txt
loki_api_client-0.1.0.dist-info/METADATA
loki_api_client-0.1.0.dist-info/WHEEL
loki_api_client-0.1.0.dist-info/top_level.txt
loki_api_client-0.1.0.dist-info/RECORD
