Metadata-Version: 2.1
Name: loki-api-client
Version: 0.1.0
Summary: A simple python wrapper for the Loki API
Home-page: https://github.com/4n4nd/loki-api-client-python/
Author: Anand Sanmukhani
Author-email: asanmukh@redhat.com
License: MIT
Project-URL: Documentation, https://pyscaffold.org/
Platform: any
Classifier: Development Status :: 4 - Beta
Classifier: Programming Language :: Python
Requires-Python: >=3.6
License-File: LICENSE.txt
License-File: AUTHORS.rst
Requires-Dist: requests
Requires-Dist: importlib-metadata ; python_version < "3.8"
Provides-Extra: testing
Requires-Dist: setuptools ; extra == 'testing'
Requires-Dist: pytest ; extra == 'testing'
Requires-Dist: pytest-cov ; extra == 'testing'
